{
  "bombers": [
    {
      "id": "f9249683-1aa0-44de-8109-b536ca1fae5d",
      "path": [
        [
          89,
          95
        ],
        [
          89,
          96
        ],
        [
          89,
          97
        ],
        [
          90,
          97
        ],
        [
          91,
          97
        ]
      ],
      "bombs": [
        [
          89,
          97
        ]
      ]
    },
    {
      "id": "5beb568b-b6ce-4119-adf2-2493e430a935",
      "path": [
        [
          89,
          95
        ],
        [
          89,
          96
        ],
        [
          89,
          97
        ],
        [
          90,
          97
        ],
        [
          91,
          97
        ]
      ],
      "bombs": [
        [
          89,
          97
        ]
      ]
    },
    {
      "id": "88e2ccde-9876-42e2-bd6f-9216c6cf4b8f",
      "path": [
        [
          89,
          95
        ],
        [
          89,
          96
        ],
        [
          89,
          97
        ],
        [
          90,
          97
        ],
        [
          91,
          97
        ]
      ],
      "bombs": [
        [
          89,
          97
        ]
      ]
    }
  ]
}