{
  "player": "Чайная терапия",
  "round": "datsjinglebang-test-4",
  "map_size": [
    167,
    167
  ],
  "bombers": [
    {
      "id": "b7d74fb3-3d87-454a-a588-17898503ae58",
      "alive": true,
      "pos": [
        156,
        32
      ],
      "armor": 0,
      "bombs_available": 1,
      "can_move": true,
      "tier": "top_100",
      "safe_time": 0
    },
    {
      "id": "dd68eeb8-dd79-4b74-967e-6c8d3db94e4f",
      "alive": true,
      "pos": [
        156,
        33
      ],
      "armor": 0,
      "bombs_available": 1,
      "can_move": true,
      "tier": "top_100",
      "safe_time": 0
    },
    {
      "id": "b16e5e7c-6ef4-424e-93b8-bfdd8de32a10",
      "alive": true,
      "pos": [
        156,
        30
      ],
      "armor": 0,
      "bombs_available": 1,
      "can_move": true,
      "tier": "top_100",
      "safe_time": 0
    },
    {
      "id": "936bfc9a-0e92-4eb7-afef-2f6f839abc5c",
      "alive": true,
      "pos": [
        156,
        30
      ],
      "armor": 0,
      "bombs_available": 1,
      "can_move": true,
      "tier": "top_100",
      "safe_time": 0
    },
    {
      "id": "5dcabaca-e729-4fc3-8d07-c869a33a0f39",
      "alive": true,
      "pos": [
        157,
        32
      ],
      "armor": 0,
      "bombs_available": 1,
      "can_move": true,
      "tier": "top_100",
      "safe_time": 0
    },
    {
      "id": "d8ada34f-8bca-4223-8819-0553fad7b48e",
      "alive": true,
      "pos": [
        156,
        30
      ],
      "armor": 0,
      "bombs_available": 1,
      "can_move": true,
      "tier": "top_100",
      "safe_time": 0
    }
  ],
  "arena": {
    "obstacles": [
      [
        158,
        32
      ],
      [
        152,
        33
      ],
      [
        157,
        26
      ],
      [
        159,
        29
      ],
      [
        153,
        36
      ],
      [
        157,
        36
      ],
      [
        154,
        29
      ],
      [
        153,
        26
      ],
      [
        159,
        26
      ],
      [
        161,
        29
      ],
      [
        153,
        34
      ],
      [
        158,
        28
      ],
      [
        152,
        29
      ],
      [
        158,
        34
      ],
      [
        154,
        36
      ],
      [
        157,
        27
      ],
      [
        153,
        29
      ],
      [
        158,
        29
      ],
      [
        156,
        36
      ],
      [
        156,
        27
      ],
      [
        156,
        29
      ],
      [
        151,
        32
      ],
      [
        161,
        32
      ],
      [
        160,
        34
      ],
      [
        160,
        35
      ],
      [
        158,
        36
      ],
      [
        158,
        37
      ],
      [
        156,
        38
      ],
      [
        162,
        32
      ],
      [
        159,
        28
      ],
      [
        154,
        31
      ],
      [
        159,
        34
      ],
      [
        151,
        33
      ],
      [
        156,
        34
      ],
      [
        152,
        27
      ],
      [
        158,
        27
      ],
      [
        157,
        29
      ],
      [
        154,
        34
      ],
      [
        154,
        26
      ],
      [
        155,
        30
      ],
      [
        152,
        32
      ],
      [
        160,
        36
      ],
      [
        154,
        37
      ],
      [
        156,
        28
      ],
      [
        153,
        32
      ],
      [
        159,
        35
      ],
      [
        152,
        31
      ],
      [
        157,
        37
      ],
      [
        154,
        27
      ]
    ],
    "walls": [
      [
        154,
        35
      ],
      [
        158,
        35
      ],
      [
        157,
        30
      ],
      [
        160,
        33
      ],
      [
        161,
        30
      ],
      [
        157,
        35
      ],
      [
        160,
        30
      ],
      [
        160,
        31
      ],
      [
        156,
        25
      ],
      [
        153,
        30
      ],
      [
        160,
        28
      ],
      [
        155,
        36
      ],
      [
        151,
        30
      ],
      [
        160,
        32
      ],
      [
        156,
        35
      ],
      [
        155,
        32
      ],
      [
        155,
        34
      ],
      [
        153,
        35
      ],
      [
        155,
        35
      ],
      [
        155,
        37
      ],
      [
        155,
        27
      ],
      [
        155,
        26
      ],
      [
        155,
        28
      ],
      [
        152,
        35
      ],
      [
        160,
        27
      ],
      [
        160,
        29
      ],
      [
        155,
        33
      ],
      [
        152,
        30
      ],
      [
        158,
        30
      ],
      [
        159,
        30
      ]
    ],
    "bombs": []
  },
  "enemies": [],
  "mobs": [
    {
      "id": "04b16009-1113-5dc2-7458-28d8c155803f",
      "type": "patrol",
      "pos": [
        158,
        26
      ],
      "safe_time": 0
    }
  ],
  "code": 0,
  "errors": [],
  "raw_score": 0
}